redis_entities/__init__.py
redis_entities/base_entity.py
redis_entities/exceptions.py
redis_entities/hashmap_entity.py
redis_entities/list_entity.py
redis_entities/set_entity.py
redis_entities/mixins/__init__.py
redis_entities/mixins/authenticated_encryption_mixin.py
redis_entities/mixins/deterministic_authenticated_encryption_mixin.py
redis_entities/mixins/hashed_identifier_mixin.py
redis_entities/mixins/mixin_base.py
redis_entities-1.0.8.dist-info/LICENSE
redis_entities-1.0.8.dist-info/METADATA
redis_entities-1.0.8.dist-info/WHEEL
redis_entities-1.0.8.dist-info/top_level.txt
redis_entities-1.0.8.dist-info/RECORD
