Metadata-Version: 2.1
Name: redis-entities
Version: 1.0.8
Summary: Redis Entities
Home-page: https://github.com/tibotix/redis_entities
Author: Tibotix
Author-email: tizian@seehaus.net
Requires-Python: >=3.8, <4
License-File: LICENSE
Requires-Dist: pycryptodome (>=3.14.1)
Requires-Dist: type-utils (>=1.0.2)
Provides-Extra: test
Requires-Dist: pytest ; extra == 'test'
Requires-Dist: fakeredis ; extra == 'test'
